<?xml version="1.0" encoding="utf-8"?>
<ThuNgans>
  <TamUng>
    <Nam>2021</Nam>
    <Thang>8</Thang>
    <SoTamUng>2</SoTamUng>
  </TamUng>
  <HoanUng>
    <Nam>2021</Nam>
    <Thang>4</Thang>
    <SoHoanUng>3</SoHoanUng>
  </HoanUng>
  <PhieuChi>
    <Nam>2021</Nam>
    <Thang>1</Thang>
    <SoPhieuChi>1</SoPhieuChi>
  </PhieuChi>
  <PhieuThus>
    <User>
      <Id>1</Id>
      <SoQuyen>1</SoQuyen>
      <SoPhieu>26</SoPhieu>
    </User>
    <User>
      <Id>2</Id>
      <SoQuyen>3</SoQuyen>
      <SoPhieu>2</SoPhieu>
    </User>
    <User>
      <Id>3</Id>
      <SoQuyen>1</SoQuyen>
      <SoPhieu>2</SoPhieu>
    </User>
    <User>
      <Id>182</Id>
      <SoQuyen>1</SoQuyen>
      <SoPhieu>37</SoPhieu>
    </User>
    <User>
      <Id>244</Id>
      <SoQuyen>1</SoQuyen>
      <SoPhieu>1</SoPhieu>
    </User>
    <User>
      <Id>10269</Id>
      <SoQuyen>1</SoQuyen>
      <SoPhieu>1</SoPhieu>
    </User>
  </PhieuThus>
</ThuNgans>